feadme/__init__.py
feadme/cli.py
feadme/compose.py
feadme/parser.py
feadme/plotting.py
feadme/utils.py
feadme/models/__init__.py
feadme/models/disk.py
feadme/models/hung.py
feadme/models/lsq.py
feadme/samplers/base_sampler.py
feadme/samplers/nuts_sampler.py
feadme-0.1.4.dist-info/METADATA
feadme-0.1.4.dist-info/WHEEL
feadme-0.1.4.dist-info/entry_points.txt
feadme-0.1.4.dist-info/licenses/LICENSE
feadme-0.1.4.dist-info/RECORD
