Metadata-Version: 2.4
Name: feadme
Version: 0.1.4
Summary: Fast Elliptical Accretion Disk Modeling Engine
Author-email: Nicholas Earl <contact@nicholasearl.me>
License-File: LICENSE
Requires-Python: >=3.11
Requires-Dist: arviz>=0.21.0
Requires-Dist: astropy>=7.0.1
Requires-Dist: click>=8.1.8
Requires-Dist: corner>=2.2.3
Requires-Dist: dacite>=1.9.2
Requires-Dist: flax>=0.10.6
Requires-Dist: loguru>=0.7.3
Requires-Dist: notebook>=7.4.3
Requires-Dist: numpyro>=0.18.0
Requires-Dist: pandas>=2.2.3
Requires-Dist: python-box>=7.3.2
Requires-Dist: quadax>=0.2.6
Requires-Dist: seaborn>=0.13.2
Requires-Dist: tabulate>=0.9.0
Requires-Dist: uncertainties>=3.2.3
Provides-Extra: gpu
Requires-Dist: jax[cuda12]; extra == 'gpu'
Provides-Extra: tpu
Requires-Dist: jax[tpu]; extra == 'tpu'
